{
  "post_id": "198",
  "title": "**데이터 과학자를 위한 효율적인 파이썬 강좌 [8/14]: Pandas DataFrame 반복문 처리를 멈추고 대신 이렇게 하세요**",
  "base_word_count": 2101,
  "exact_30_update_wc": 2338,
  "exact_30_ground_truth_wc": 2320,
  "exact_30_overlap_ratio": 0.906,
  "paraphrase_25_update_wc": 2435,
  "paraphrase_25_ground_truth_wc": 2435,
  "paraphrase_25_overlap_ratio": 0.863,
  "fragment_20_update_wc": 951,
  "fragment_20_ground_truth_wc": 2474,
  "fragment_20_overlap_ratio": 0.608,
  "semantic_25_update_wc": 1945,
  "semantic_25_ground_truth_wc": 1944,
  "semantic_25_overlap_ratio": 1.081,
  "mixed_real_update_wc": 1750,
  "mixed_real_ground_truth_wc": 1760,
  "mixed_real_overlap_ratio": 1.195,
  "status": "generated"
}